dnnviewer/Connector.py
dnnviewer/Grapher.py
dnnviewer/Progress.py
dnnviewer/Statistics.py
dnnviewer/TestData.py
dnnviewer/__init__.py
dnnviewer/imageutils.py
dnnviewer/main.py
dnnviewer/main_model_selection.py
dnnviewer/main_network_view.py
dnnviewer/assets/dnnviewer.css
dnnviewer/bridge/AbstractActivationMapper.py
dnnviewer/bridge/AbstractModelSequence.py
dnnviewer/bridge/KerasModelSequence.py
dnnviewer/bridge/__init__.py
dnnviewer/bridge/tensorflow.py
dnnviewer/bridge/tensorflow_datasets.py
dnnviewer/layers/AbstractLayer.py
dnnviewer/layers/Convo2D.py
dnnviewer/layers/Dense.py
dnnviewer/layers/Input.py
dnnviewer/layers/__init__.py
dnnviewer/panes/__init__.py
dnnviewer/panes/bottom.py
dnnviewer/panes/center.py
dnnviewer/panes/top.py
dnnviewer/theming/SimpleColorScale.py
dnnviewer/theming/Theme.py
dnnviewer/theming/__init__.py
dnnviewer/widgets/Router.py
dnnviewer/widgets/__init__.py
dnnviewer/widgets/conv_filter_map.py
dnnviewer/widgets/font_awesome.py
dnnviewer/widgets/layer_minimax_graph.py
dnnviewer/widgets/property_list.py
dnnviewer/widgets/tabs.py
dnnviewer-0.1.0.dist-info/LICENSE
dnnviewer-0.1.0.dist-info/METADATA
dnnviewer-0.1.0.dist-info/WHEEL
dnnviewer-0.1.0.dist-info/entry_points.txt
dnnviewer-0.1.0.dist-info/top_level.txt
dnnviewer-0.1.0.dist-info/RECORD
