Metadata-Version: 2.1
Name: dnnviewer
Version: 0.1.0
Summary: Deep Neural Network inspection: view weights, gradients and activations
Home-page: https://github.com/tonio73/dnnviewer
Author: A. Hue
License: MIT
Keywords: DNN,CNN,Interpretability,Tensorflow,Keras
Platform: UNKNOWN
Classifier: Intended Audience :: Developers
Classifier: Intended Audience :: System Administrators
Classifier: Intended Audience :: Science/Research
Classifier: License :: OSI Approved :: MIT License
Classifier: Programming Language :: Python
Classifier: Programming Language :: Python :: 3
Classifier: Programming Language :: Python :: 3.5
Classifier: Programming Language :: Python :: 3.6
Classifier: Programming Language :: Python :: 3.7
Requires-Python: >=3.5
Requires-Dist: numpy
Requires-Dist: tensorflow (>=2.0)
Requires-Dist: tensorflow-datasets
Requires-Dist: plotly (>=4.0)
Requires-Dist: dash
Requires-Dist: dash-core-components
Requires-Dist: dash-html-components
Requires-Dist: dash-bootstrap-components
Requires-Dist: pillow
